mcp_data_analyzer/__init__.py
mcp_data_analyzer/__main__.py
mcp_data_analyzer/cli.py
mcp_data_analyzer/core.py
zgy_mcp_data_analzyer-0.1.0.dist-info/METADATA
zgy_mcp_data_analzyer-0.1.0.dist-info/WHEEL
zgy_mcp_data_analzyer-0.1.0.dist-info/entry_points.txt
zgy_mcp_data_analzyer-0.1.0.dist-info/top_level.txt
zgy_mcp_data_analzyer-0.1.0.dist-info/RECORD
